LICENSE
dvbctrl/__init__.py
dvbctrl/colours.py
dvbctrl/commands.py
dvbctrl/connection.py
dvbctrl/dvbstreamer.py
dvbctrl/errors.py
dvbctrl/output.py
dvbctrl/recorder.py
dvbctrl/shell.py
dvbctrl-0.3.9.dist-info/LICENSE
dvbctrl-0.3.9.dist-info/WHEEL
dvbctrl-0.3.9.dist-info/METADATA
dvbctrl-0.3.9.dist-info/RECORD
