Metadata-Version: 2.1
Name: dvbctrl
Version: 0.3.9
Summary: Controls a local dvbstreamer
Home-page: https://github.com/ccdale/dvbctrl
License: GPL-3.0-or-later
Author: ccdale
Author-email: chris.charles.allison+dvbctrl@gmail.com
Requires-Python: >=3.10,<4.0
Classifier: Development Status :: 4 - Beta
Classifier: Environment :: Console 
Classifier: Intended Audience :: Developers
Classifier: License :: OSI Approved :: GNU General Public License v3 or later (GPLv3+)
Classifier: Operating System :: POSIX :: Linux
Classifier: Programming Language :: Python :: 3
Classifier: Programming Language :: Python :: 3.10
Classifier: Topic :: Multimedia :: Video
Classifier: Topic :: Multimedia :: Video :: Capture
Requires-Dist: psutil (>=5.9.1,<6.0.0)
Project-URL: Repository, https://github.com/ccdale/dvbctrl
